legend_pygeom_hpges-0.8.2.dist-info/licenses/LICENSE
legendhpges/__init__.py
legendhpges/_version.py
legendhpges/base.py
legendhpges/bege.py
legendhpges/build_utils.py
legendhpges/draw.py
legendhpges/invcoax.py
legendhpges/make_hpge.py
legendhpges/materials.py
legendhpges/p00664b.py
legendhpges/ppc.py
legendhpges/semicoax.py
legendhpges/utils.py
legendhpges/v02160a.py
legendhpges/v02162b.py
legendhpges/v07646a.py
legend_pygeom_hpges-0.8.2.dist-info/METADATA
legend_pygeom_hpges-0.8.2.dist-info/WHEEL
legend_pygeom_hpges-0.8.2.dist-info/top_level.txt
legend_pygeom_hpges-0.8.2.dist-info/RECORD
