Metadata-Version: 2.4
Name: legend_pygeom_hpges
Version: 0.8.2
Summary: Geometry management for LEGEND HPGE detectors
Author-email: Luigi Pertoldi <gipert@pm.me>
Maintainer: The LEGEND Collaboration
License:                     GNU GENERAL PUBLIC LICENSE
Project-URL: Homepage, https://github.com/legend-exp/legend-pygeom-hpges
Project-URL: Bug Tracker, https://github.com/legend-exp/legend-pygeom-hpges/issues
Project-URL: Discussions, https://github.com/legend-exp/legend-pygeom-hpges/discussions
Project-URL: Changelog, https://github.com/legend-exp/legend-pygeom-hpges/releases
Classifier: Intended Audience :: Developers
Classifier: Intended Audience :: Science/Research
Classifier: License :: OSI Approved :: GNU General Public License v3 (GPLv3)
Classifier: Operating System :: MacOS
Classifier: Operating System :: POSIX
Classifier: Operating System :: Unix
Classifier: Programming Language :: Python
Classifier: Programming Language :: Python :: 3
Classifier: Programming Language :: Python :: 3 :: Only
Classifier: Topic :: Scientific/Engineering
Requires-Python: >=3.10
License-File: LICENSE
Requires-Dist: numpy
Requires-Dist: numba
Requires-Dist: pint!=0.24
Requires-Dist: pyg4ometry
Requires-Dist: dbetto
Requires-Dist: awkward
Provides-Extra: all
Requires-Dist: legend-pygeom-hpges[docs,test]; extra == "all"
Provides-Extra: docs
Requires-Dist: furo; extra == "docs"
Requires-Dist: myst-parser; extra == "docs"
Requires-Dist: sphinx; extra == "docs"
Requires-Dist: sphinx-copybutton; extra == "docs"
Provides-Extra: test
Requires-Dist: pre-commit; extra == "test"
Requires-Dist: pylegendtestdata; extra == "test"
Requires-Dist: pytest>=6.0; extra == "test"
Requires-Dist: pytest-cov; extra == "test"
Dynamic: license-file
